raghav/__init__.py
tests/__init__.py
tests/test_string.py
raghav-1.0.2.dist-info/LICENSE
raghav-1.0.2.dist-info/METADATA
raghav-1.0.2.dist-info/WHEEL
raghav-1.0.2.dist-info/top_level.txt
raghav-1.0.2.dist-info/RECORD
