Metadata-Version: 2.1
Name: raghav
Version: 1.0.2
Summary: Test String Manip Functions
Home-page: UNKNOWN
Author-email: raghav.thapa@datadoghq.com
License: UNKNOWN
Keywords: string,manipulation,test
Platform: UNKNOWN
Classifier: License :: OSI Approved :: MIT License
Classifier: Intended Audience :: Developers
Classifier: Programming Language :: Python :: 3 :: Only
